easy_cache/__init__.py
easy_cache/_version.py
easy_cache/abc.py
easy_cache/compat.py
easy_cache/core.py
easy_cache/decorators.py
easy_cache/utils.py
easy_cache/contrib/__init__.py
easy_cache/contrib/redis_cache.py
easy_cache-2.0.0.dist-info/LICENSE
easy_cache-2.0.0.dist-info/METADATA
easy_cache-2.0.0.dist-info/WHEEL
easy_cache-2.0.0.dist-info/top_level.txt
easy_cache-2.0.0.dist-info/RECORD
