Metadata-Version: 2.1
Name: easy-cache
Version: 2.0.0
Summary: Useful cache decorators for methods and properties
Home-page: https://github.com/Bahus/easy_cache
Author: Oleg Churkin
Author-email: bahusoff@gmail.com
License: MIT
Keywords: cache,decorator,invalidation,memcached,redis,django
Platform: Platform Independent
Classifier: Development Status :: 5 - Production/Stable
Classifier: Environment :: Web Environment
Classifier: Operating System :: OS Independent
Classifier: Programming Language :: Python
Classifier: Programming Language :: Python :: 3.7
Classifier: Programming Language :: Python :: 3.8
Classifier: Programming Language :: Python :: 3.9
Classifier: Programming Language :: Python :: 3.10
Classifier: Topic :: Software Development :: Libraries :: Python Modules
Classifier: Intended Audience :: Developers
Classifier: License :: OSI Approved :: MIT License
Provides-Extra: tests
License-File: LICENSE
